mpi_pytest-2025.6.0.dist-info/licenses/LICENSE
pytest_mpi/__init__.py
pytest_mpi/parallel_assert.py
pytest_mpi/plugin.py
mpi_pytest-2025.6.0.dist-info/METADATA
mpi_pytest-2025.6.0.dist-info/WHEEL
mpi_pytest-2025.6.0.dist-info/entry_points.txt
mpi_pytest-2025.6.0.dist-info/top_level.txt
mpi_pytest-2025.6.0.dist-info/RECORD
