Metadata-Version: 2.4
Name: mpi-pytest
Version: 2025.6.0
Summary: A pytest plugin for executing tests in parallel with MPI
Author-email: Connor Ward <c.ward20@imperial.ac.uk>, Jack Betteridge <j.betteridge@imperial.ac.uk>
License-Expression: LGPL-3.0-or-later
Classifier: Programming Language :: Python :: 3
Classifier: Framework :: Pytest
Classifier: Operating System :: MacOS
Classifier: Operating System :: POSIX :: Linux
Classifier: Operating System :: Microsoft :: Windows
Requires-Python: >=3.9
License-File: LICENSE
Requires-Dist: mpi4py
Requires-Dist: pytest
Dynamic: license-file
